{"v":"5.6.6","fr":25,"ip":0,"op":101,"w":720,"h":576,"nm":"Comp 7","ddd":0,"assets":[],"layers":[{"ddd":0,"ind":1,"ty":4,"nm":"About Outlines","sr":1,"ks":{"o":{"a":0,"k":100,"ix":11},"r":{"a":0,"k":0,"ix":10},"p":{"a":0,"k":[162.585,341.65,0],"ix":2},"a":{"a":0,"k":[0,0,0],"ix":1},"s":{"a":0,"k":[100,100,100],"ix":6}},"ao":0,"shapes":[{"ty":"gr","it":[{"ind":0,"ty":"sh","ix":1,"ks":{"a":0,"k":{"i":[[0,0],[0,0],[0,0],[0,0],[0,0],[0,0],[0,0],[0,0]],"o":[[0,0],[0,0],[0,0],[0,0],[0,0],[0,0],[0,0],[0,0]],"v":[[107.735,0],[65.105,-102.66],[41.035,-102.66],[-2.03,0],[24.94,0],[32.48,-20.155],[72.21,-20.155],[80.185,0]],"c":true},"ix":2},"nm":"A","mn":"ADBE Vector Shape - Group","hd":false},{"ind":1,"ty":"sh","ix":2,"ks":{"a":0,"k":{"i":[[0,0],[0,0],[0,0]],"o":[[0,0],[0,0],[0,0]],"v":[[65.395,-40.02],[39.585,-40.02],[52.635,-75.255]],"c":true},"ix":2},"nm":"A","mn":"ADBE Vector Shape - Group","hd":false},{"ty":"mm","mm":1,"nm":"Merge Paths 1","mn":"ADBE Vector Filter - Merge","hd":false},{"ty":"st","c":{"a":0,"k":[1,1,1,1],"ix":3},"o":{"a":0,"k":100,"ix":4},"w":{"a":0,"k":5,"ix":5},"lc":1,"lj":1,"ml":4,"bm":0,"nm":"Stroke 1","mn":"ADBE Vector Graphic - Stroke","hd":false},{"ty":"tr","p":{"a":0,"k":[0,0],"ix":2},"a":{"a":0,"k":[0,0],"ix":1},"s":{"a":0,"k":[100,100],"ix":3},"r":{"a":0,"k":0,"ix":6},"o":{"a":0,"k":100,"ix":7},"sk":{"a":0,"k":0,"ix":4},"sa":{"a":0,"k":0,"ix":5},"nm":"Transform"}],"nm":"A","np":5,"cix":2,"bm":0,"ix":1,"mn":"ADBE Vector Group","hd":false},{"ty":"gr","it":[{"ind":0,"ty":"sh","ix":1,"ks":{"a":0,"k":{"i":[[1.595,4.592],[2.948,3.48],[4.205,2.03],[5.22,0],[3.673,-2.03],[2.03,-2.415],[0,0],[0,0],[0,0],[0,0],[0,0],[0,0],[0,0],[-4.302,-1.98],[-4.835,0],[-4.255,2.125],[-2.95,3.53],[-1.547,4.64],[0,5.027]],"o":[[-1.595,-4.59],[-2.95,-3.48],[-4.205,-2.03],[-5.317,0],[-3.675,2.03],[0,0],[0,0],[0,0],[0,0],[0,0],[0,0],[0,0],[2.32,3.675],[4.3,1.98],[5.413,0],[4.253,-2.125],[2.948,-3.528],[1.545,-4.64],[0,-5.025]],"v":[[193.066,-50.823],[186.251,-62.93],[175.521,-71.195],[161.383,-74.24],[147.898,-71.195],[139.343,-64.525],[139.053,-64.525],[139.053,-109.62],[115.273,-109.62],[115.273,0],[137.168,0],[137.168,-9.425],[137.458,-9.425],[147.391,-0.943],[161.093,2.03],[175.593,-1.16],[186.396,-9.643],[193.138,-21.895],[195.458,-36.395]],"c":true},"ix":2},"nm":"b","mn":"ADBE Vector Shape - Group","hd":false},{"ind":1,"ty":"sh","ix":2,"ks":{"a":0,"k":{"i":[[0.725,-2.27],[1.45,-1.74],[2.125,-1.063],[2.803,0],[2.125,1.065],[1.498,1.74],[0.82,2.225],[0,2.32],[-0.822,2.225],[-1.5,1.74],[-2.127,1.065],[-2.707,0],[-2.127,-1.063],[-1.45,-1.69],[-0.725,-2.223],[0,-2.32]],"o":[[-0.725,2.272],[-1.45,1.74],[-2.127,1.065],[-2.707,0],[-2.127,-1.063],[-1.5,-1.74],[-0.822,-2.223],[0,-2.32],[0.82,-2.223],[1.498,-1.74],[2.125,-1.063],[2.803,0],[2.125,1.065],[1.45,1.692],[0.725,2.225],[0,2.32]],"v":[[171.461,-29.508],[168.198,-23.49],[162.833,-19.285],[155.438,-17.69],[148.188,-19.285],[142.751,-23.49],[139.271,-29.435],[138.038,-36.25],[139.271,-43.065],[142.751,-49.01],[148.188,-53.215],[155.438,-54.81],[162.833,-53.215],[168.198,-49.083],[171.461,-43.21],[172.548,-36.395]],"c":true},"ix":2},"nm":"b","mn":"ADBE Vector Shape - Group","hd":false},{"ty":"mm","mm":1,"nm":"Merge Paths 1","mn":"ADBE Vector Filter - Merge","hd":false},{"ty":"st","c":{"a":0,"k":[1,1,1,1],"ix":3},"o":{"a":0,"k":100,"ix":4},"w":{"a":0,"k":5,"ix":5},"lc":1,"lj":1,"ml":4,"bm":0,"nm":"Stroke 1","mn":"ADBE Vector Graphic - Stroke","hd":false},{"ty":"tr","p":{"a":0,"k":[0,0],"ix":2},"a":{"a":0,"k":[0,0],"ix":1},"s":{"a":0,"k":[100,100],"ix":3},"r":{"a":0,"k":0,"ix":6},"o":{"a":0,"k":100,"ix":7},"sk":{"a":0,"k":0,"ix":4},"sa":{"a":0,"k":0,"ix":5},"nm":"Transform"}],"nm":"b","np":5,"cix":2,"bm":0,"ix":2,"mn":"ADBE Vector Group","hd":false},{"ty":"gr","it":[{"ind":0,"ty":"sh","ix":1,"ks":{"a":0,"k":{"i":[[2.125,4.737],[3.673,3.287],[4.833,1.74],[5.51,0],[4.88,-1.74],[3.625,-3.285],[2.125,-4.735],[0,-5.895],[-2.127,-4.785],[-3.625,-3.335],[-4.882,-1.835],[-5.415,0],[-4.835,1.835],[-3.675,3.335],[-2.127,4.785],[0,5.897]],"o":[[-2.127,-4.735],[-3.675,-3.285],[-4.835,-1.74],[-5.415,0],[-4.882,1.74],[-3.625,3.287],[-2.127,4.737],[0,5.897],[2.125,4.785],[3.625,3.335],[4.88,1.835],[5.51,0],[4.833,-1.835],[3.673,-3.335],[2.125,-4.785],[0,-5.895]],"v":[[283.908,-52.345],[275.208,-64.38],[262.448,-71.92],[246.933,-74.53],[231.49,-71.92],[218.73,-64.38],[210.103,-52.345],[206.913,-36.395],[210.103,-20.372],[218.73,-8.193],[231.49,-0.435],[246.933,2.32],[262.448,-0.435],[275.208,-8.193],[283.908,-20.372],[287.098,-36.395]],"c":true},"ix":2},"nm":"o","mn":"ADBE Vector Shape - Group","hd":false},{"ind":1,"ty":"sh","ix":2,"ks":{"a":0,"k":{"i":[[0.725,-2.223],[1.45,-1.788],[2.125,-1.063],[2.803,0],[2.125,1.065],[1.45,1.79],[0.725,2.225],[0,2.32],[-0.725,2.225],[-1.402,1.692],[-2.127,1.065],[-2.805,0],[-2.127,-1.063],[-1.45,-1.69],[-0.775,-2.223],[0,-2.32]],"o":[[-0.725,2.225],[-1.45,1.79],[-2.127,1.065],[-2.805,0],[-2.127,-1.063],[-1.45,-1.788],[-0.725,-2.223],[0,-2.32],[0.725,-2.223],[1.4,-1.69],[2.125,-1.063],[2.803,0],[2.125,1.065],[1.45,1.692],[0.773,2.225],[0,2.32]],"v":[[263.1,-29.58],[259.838,-23.562],[254.473,-19.285],[247.078,-17.69],[239.683,-19.285],[234.318,-23.562],[231.055,-29.58],[229.968,-36.395],[231.055,-43.21],[234.245,-49.083],[239.538,-53.215],[246.933,-54.81],[254.328,-53.215],[259.693,-49.083],[263.028,-43.21],[264.188,-36.395]],"c":true},"ix":2},"nm":"o","mn":"ADBE Vector Shape - Group","hd":false},{"ty":"mm","mm":1,"nm":"Merge Paths 1","mn":"ADBE Vector Filter - Merge","hd":false},{"ty":"st","c":{"a":0,"k":[1,1,1,1],"ix":3},"o":{"a":0,"k":100,"ix":4},"w":{"a":0,"k":5,"ix":5},"lc":1,"lj":1,"ml":4,"bm":0,"nm":"Stroke 1","mn":"ADBE Vector Graphic - Stroke","hd":false},{"ty":"tr","p":{"a":0,"k":[0,0],"ix":2},"a":{"a":0,"k":[0,0],"ix":1},"s":{"a":0,"k":[100,100],"ix":3},"r":{"a":0,"k":0,"ix":6},"o":{"a":0,"k":100,"ix":7},"sk":{"a":0,"k":0,"ix":4},"sa":{"a":0,"k":0,"ix":5},"nm":"Transform"}],"nm":"o","np":5,"cix":2,"bm":0,"ix":3,"mn":"ADBE Vector Group","hd":false},{"ty":"gr","it":[{"ind":0,"ty":"sh","ix":1,"ks":{"a":0,"k":{"i":[[0,0],[0,0],[0,0],[0,0],[2.175,-3.093],[4.155,0],[1.353,0.822],[0.82,1.45],[0.29,1.837],[0,2.03],[0,0],[0,0],[0,0],[-0.92,-3.528],[-2.08,-2.755],[-3.335,-1.74],[-4.835,0],[-2.272,0.675],[-1.885,1.065],[-1.402,1.45],[-0.87,1.645],[0,0],[0,0]],"o":[[0,0],[0,0],[0,0],[0,4.157],[-2.175,3.095],[-2.225,0],[-1.355,-0.82],[-0.822,-1.45],[-0.29,-1.835],[0,0],[0,0],[0,0],[0,3.675],[0.918,3.53],[2.078,2.755],[3.335,1.74],[2.513,0],[2.27,-0.677],[1.885,-1.063],[1.4,-1.45],[0,0],[0,0],[0,0]],"v":[[372.646,0],[372.646,-72.21],[348.866,-72.21],[348.866,-33.205],[345.604,-22.33],[336.106,-17.69],[330.741,-18.923],[327.479,-22.33],[325.811,-27.26],[325.376,-33.06],[325.376,-72.21],[301.451,-72.21],[301.451,-27.55],[302.829,-16.747],[307.324,-7.322],[315.444,-0.58],[327.696,2.03],[334.874,1.015],[341.109,-1.595],[346.039,-5.365],[349.446,-10.005],[349.736,-10.005],[349.736,0]],"c":true},"ix":2},"nm":"u","mn":"ADBE Vector Shape - Group","hd":false},{"ty":"st","c":{"a":0,"k":[1,1,1,1],"ix":3},"o":{"a":0,"k":100,"ix":4},"w":{"a":0,"k":5,"ix":5},"lc":1,"lj":1,"ml":4,"bm":0,"nm":"Stroke 1","mn":"ADBE Vector Graphic - Stroke","hd":false},{"ty":"tr","p":{"a":0,"k":[0,0],"ix":2},"a":{"a":0,"k":[0,0],"ix":1},"s":{"a":0,"k":[100,100],"ix":3},"r":{"a":0,"k":0,"ix":6},"o":{"a":0,"k":100,"ix":7},"sk":{"a":0,"k":0,"ix":4},"sa":{"a":0,"k":0,"ix":5},"nm":"Transform"}],"nm":"u","np":3,"cix":2,"bm":0,"ix":4,"mn":"ADBE Vector Group","hd":false},{"ty":"gr","it":[{"ind":0,"ty":"sh","ix":1,"ks":{"a":0,"k":{"i":[[0,0],[0,0],[0,0],[0,0],[0,0],[0,0],[0,0],[0,0],[0,0],[0,0],[-0.87,-3.149],[-1.982,-2.277],[-3.287,-1.21],[-4.835,0],[-2.515,0.435],[-1.645,0.58],[0,0],[1.305,-0.193],[1.16,0],[1.305,1.699],[0,3.396],[0,0]],"o":[[0,0],[0,0],[0,0],[0,0],[0,0],[0,0],[0,0],[0,0],[0,0],[0,3.876],[0.87,3.149],[1.98,2.279],[3.285,1.21],[2.513,0],[2.513,-0.435],[0,0],[-0.87,0.387],[-1.305,0.195],[-3.385,0],[-1.305,-1.699],[0,0],[0,0]],"v":[[433.981,-54.52],[433.981,-72.21],[417.016,-72.21],[417.016,-91.205],[393.671,-91.205],[393.671,-72.21],[382.216,-72.21],[382.216,-54.52],[393.816,-54.52],[393.816,-23.991],[395.121,-13.451],[399.398,-5.311],[407.301,-0.077],[419.481,1.74],[427.021,1.087],[433.256,-0.435],[432.966,-17.835],[429.703,-16.965],[426.006,-16.675],[418.973,-19.222],[417.016,-26.864],[417.016,-54.52]],"c":true},"ix":2},"nm":"t","mn":"ADBE Vector Shape - Group","hd":false},{"ty":"st","c":{"a":0,"k":[1,1,1,1],"ix":3},"o":{"a":0,"k":100,"ix":4},"w":{"a":0,"k":5,"ix":5},"lc":1,"lj":1,"ml":4,"bm":0,"nm":"Stroke 1","mn":"ADBE Vector Graphic - Stroke","hd":false},{"ty":"tr","p":{"a":0,"k":[0,0],"ix":2},"a":{"a":0,"k":[0,0],"ix":1},"s":{"a":0,"k":[100,100],"ix":3},"r":{"a":0,"k":0,"ix":6},"o":{"a":0,"k":100,"ix":7},"sk":{"a":0,"k":0,"ix":4},"sa":{"a":0,"k":0,"ix":5},"nm":"Transform"}],"nm":"t","np":3,"cix":2,"bm":0,"ix":5,"mn":"ADBE Vector Group","hd":false},{"ty":"tm","s":{"a":0,"k":0,"ix":1},"e":{"a":1,"k":[{"i":{"x":[0.833],"y":[0.833]},"o":{"x":[0.167],"y":[0.167]},"t":0,"s":[0]},{"t":75,"s":[100]}],"ix":2},"o":{"a":0,"k":0,"ix":3},"m":1,"ix":6,"nm":"Trim Paths 1","mn":"ADBE Vector Filter - Trim","hd":false},{"ty":"fl","c":{"a":0,"k":[1,1,1,1],"ix":4},"o":{"a":1,"k":[{"i":{"x":[0.833],"y":[0.833]},"o":{"x":[0.167],"y":[0.167]},"t":0,"s":[0]},{"i":{"x":[0.833],"y":[0.833]},"o":{"x":[0.167],"y":[0.167]},"t":75,"s":[0]},{"t":100,"s":[100]}],"ix":5},"r":1,"bm":0,"nm":"Fill 1","mn":"ADBE Vector Graphic - Fill","hd":false}],"ip":0,"op":750,"st":0,"bm":0}],"markers":[]}